smt/__init__.py
smt/proof.py
smt/store.py
smt/tree.py
smt/utils.py
tests/__init__.py
tests/test_tree.py
sparse_merkle_tree-0.3.0.dist-info/LICENSE
sparse_merkle_tree-0.3.0.dist-info/METADATA
sparse_merkle_tree-0.3.0.dist-info/WHEEL
sparse_merkle_tree-0.3.0.dist-info/top_level.txt
sparse_merkle_tree-0.3.0.dist-info/RECORD
