Metadata-Version: 2.1
Name: sparse-merkle-tree
Version: 0.3.0
Summary: A Sparse Merkle Tree for a key/value map
Home-page: https://github.com/davebryson/sparse-merkle-tree
Author: Dave Bryson
License: Apache 2.0
Project-URL: Source, https://github.com/davebryson/sparse-merkle-tree
Keywords: merkletree
Platform: unix
Platform: linux
Platform: osx
Platform: cygwin
Platform: win32
Classifier: Development Status :: 3 - Alpha
Classifier: Intended Audience :: Developers
Classifier: License :: OSI Approved :: Apache Software License
Classifier: Programming Language :: Python :: 3.9
Requires-Python: >=3.9
License-File: LICENSE
Provides-Extra: dev
Requires-Dist: pytest ; extra == 'dev'
Requires-Dist: twine ; extra == 'dev'
Requires-Dist: black ; extra == 'dev'
Requires-Dist: build ; extra == 'dev'
